ask_sdk_model/__init__.py
ask_sdk_model/__version__.py
ask_sdk_model/application.py
ask_sdk_model/cause.py
ask_sdk_model/connection_completed.py
ask_sdk_model/context.py
ask_sdk_model/device.py
ask_sdk_model/dialog_state.py
ask_sdk_model/directive.py
ask_sdk_model/intent.py
ask_sdk_model/intent_confirmation_status.py
ask_sdk_model/intent_request.py
ask_sdk_model/launch_request.py
ask_sdk_model/list_slot_value.py
ask_sdk_model/permission_status.py
ask_sdk_model/permissions.py
ask_sdk_model/person.py
ask_sdk_model/py.typed
ask_sdk_model/request.py
ask_sdk_model/request_envelope.py
ask_sdk_model/response.py
ask_sdk_model/response_envelope.py
ask_sdk_model/scope.py
ask_sdk_model/session.py
ask_sdk_model/session_ended_error.py
ask_sdk_model/session_ended_error_type.py
ask_sdk_model/session_ended_reason.py
ask_sdk_model/session_ended_request.py
ask_sdk_model/session_resumed_request.py
ask_sdk_model/simple_slot_value.py
ask_sdk_model/slot.py
ask_sdk_model/slot_confirmation_status.py
ask_sdk_model/slot_value.py
ask_sdk_model/status.py
ask_sdk_model/supported_interfaces.py
ask_sdk_model/task.py
ask_sdk_model/user.py
ask_sdk_model/authorization/__init__.py
ask_sdk_model/authorization/authorization_grant_body.py
ask_sdk_model/authorization/authorization_grant_request.py
ask_sdk_model/authorization/grant.py
ask_sdk_model/authorization/grant_type.py
ask_sdk_model/authorization/py.typed
ask_sdk_model/canfulfill/__init__.py
ask_sdk_model/canfulfill/can_fulfill_intent.py
ask_sdk_model/canfulfill/can_fulfill_intent_request.py
ask_sdk_model/canfulfill/can_fulfill_intent_values.py
ask_sdk_model/canfulfill/can_fulfill_slot.py
ask_sdk_model/canfulfill/can_fulfill_slot_values.py
ask_sdk_model/canfulfill/can_understand_slot_values.py
ask_sdk_model/canfulfill/py.typed
ask_sdk_model/dialog/__init__.py
ask_sdk_model/dialog/confirm_intent_directive.py
ask_sdk_model/dialog/confirm_slot_directive.py
ask_sdk_model/dialog/delegate_directive.py
ask_sdk_model/dialog/delegate_request_directive.py
ask_sdk_model-1.82.0.dist-info/LICENSE
ask_sdk_model-1.82.0.dist-info/METADATA
ask_sdk_model-1.82.0.dist-info/NOTICE.txt
ask_sdk_model-1.82.0.dist-info/WHEEL
ask_sdk_model-1.82.0.dist-info/top_level.txt
ask_sdk_model-1.82.0.dist-info/RECORD
